hoc2swc/__init__.py
tests/__init__.py
tests/test_all.py
hoc2swc-0.1.2.dist-info/LICENSE.md
hoc2swc-0.1.2.dist-info/METADATA
hoc2swc-0.1.2.dist-info/WHEEL
hoc2swc-0.1.2.dist-info/top_level.txt
hoc2swc-0.1.2.dist-info/RECORD
