Metadata-Version: 2.1
Name: hoc2swc
Version: 0.1.2
Summary: Convert NEURON simulator .HOC files to .SWC morphology format
Home-page: https://github.com/justasb/hoc2swc
Author: Justas Birgiolas
Author-email: justas@asu.edu
License: UNKNOWN
Platform: UNKNOWN
Classifier: Programming Language :: Python :: 3
Classifier: Operating System :: OS Independent
